{
  "version": "1.7.14",
  "description": "Intelligent Kubernetes Control Center",
  "homepage": "https://kubegraf.io",
  "license": "Apache-2.0",
  "url": "https://github.com/kubegraf/kubegraf/releases/download/v1.7.14/kubegraf-windows-amd64.zip",
  "hash": "4d51f5182ef37a6b467ecd5abbc23d7c13f9f5bebfb34ddaf236798e3d28de17",
  "bin": "kubegraf.exe",
  "checkver": {
    "github": "https://github.com/kubegraf/kubegraf"
  },
  "autoupdate": {
    "url": "https://github.com/kubegraf/kubegraf/releases/download/v$version/kubegraf-windows-amd64.zip"
  }
}
